meshflow/__init__.py
meshflow-0.0.1.dist-info/METADATA
meshflow-0.0.1.dist-info/WHEEL
meshflow-0.0.1.dist-info/top_level.txt
meshflow-0.0.1.dist-info/RECORD
